wiz_presto/__init__.py
wiz_presto/client.py
wiz_presto-1.0.0.dist-info/METADATA
wiz_presto-1.0.0.dist-info/RECORD
wiz_presto-1.0.0.dist-info/WHEEL
wiz_presto-1.0.0.dist-info/top_level.txt
